medmnist/__init__.py
medmnist/__main__.py
medmnist/dataset.py
medmnist/evaluator.py
medmnist/info.py
medmnist/utils.py
medmnist-3.0.2.dist-info/LICENSE
medmnist-3.0.2.dist-info/METADATA
medmnist-3.0.2.dist-info/WHEEL
medmnist-3.0.2.dist-info/top_level.txt
medmnist-3.0.2.dist-info/zip-safe
medmnist-3.0.2.dist-info/RECORD
