Metadata-Version: 2.1
Name: medmnist
Version: 3.0.2
Summary: [MedMNIST+] 18x Standardized Datasets for 2D and 3D Biomedical Image Classification with Multiple Size Options: 28 (MNIST-Like), 64, 128, and 224
Home-page: https://github.com/MedMNIST/MedMNIST/
Author: MedMNIST Team
Author-email: jiancheng.yang@epfl.ch
License: Apache-2.0 License
Classifier: License :: OSI Approved :: Apache Software License
Classifier: Programming Language :: Python
Classifier: Programming Language :: Python :: 3 :: Only
Requires-Python: >=3.6.0
License-File: LICENSE
